pyaid/__init__.py
pyaid/base.py
pyaid/tests/__init__.py
pyaid/tests/test_base.py
pyaid-0.0.4.dist-info/LICENSE
pyaid-0.0.4.dist-info/METADATA
pyaid-0.0.4.dist-info/WHEEL
pyaid-0.0.4.dist-info/top_level.txt
pyaid-0.0.4.dist-info/zip-safe
pyaid-0.0.4.dist-info/RECORD
