Metadata-Version: 2.1
Name: pyaid
Version: 0.0.4
Summary: A package of helpful utility code for general Python development.
Home-page: https://github.com/jddecarlo/pyaid
Author: Jonathan DeCarlo
Author-email: everythingiwanted.sortof@gmail.com
License: MIT
Download-URL: https://github.com/jddecarlo/pyaid/releases/download/v0.0.4/pyaid-0.0.4-py3-none-any.whl
Keywords: Python,Library
Platform: any
Classifier: Development Status :: 3 - Alpha
Classifier: Intended Audience :: Developers
Classifier: License :: OSI Approved :: MIT License
Classifier: Operating System :: OS Independent
Classifier: Programming Language :: Python :: 3.8
Requires-Python: >=3.8.*
